adi_super_memory/__init__.py
adi_super_memory/audit.py
adi_super_memory/core.py
adi_super_memory/embeddings.py
adi_super_memory/py.typed
adi_super_memory/retrieval.py
adi_super_memory/stm.py
adi_super_memory/types.py
adi_super_memory/adapters/__init__.py
adi_super_memory/adapters/autogen.py
adi_super_memory/adapters/langchain.py
adi_super_memory/adapters/langgraph.py
adi_super_memory/adapters/semantic_kernel.py
adi_super_memory/auth/__init__.py
adi_super_memory/auth/keys.py
adi_super_memory/backends/__init__.py
adi_super_memory/backends/base.py
adi_super_memory/backends/inmemory.py
adi_super_memory/backends/postgres.py
adi_super_memory/backends/qdrant.py
adi_super_memory/backends/sqlite.py
adi_super_memory/distillers/__init__.py
adi_super_memory/distillers/deterministic.py
adi_super_memory/distillers/openai_chat.py
adi_super_memory/policy/__init__.py
adi_super_memory/policy/memory_policy.py
adi_super_memory/policy/tool_policy.py
adi_super_memory/robotics/__init__.py
adi_super_memory/robotics/runtime.py
adi_super_memory/safety/__init__.py
adi_super_memory/safety/modes.py
adi_super_memory/safety/redaction.py
adi_super_memory/server/__init__.py
adi_super_memory/server/app.py
adi_super_memory-0.4.0.dist-info/METADATA
adi_super_memory-0.4.0.dist-info/WHEEL
adi_super_memory-0.4.0.dist-info/top_level.txt
adi_super_memory-0.4.0.dist-info/RECORD
